rithm/_enums.py
rithm/fraction.py
rithm/__init__.py
rithm/enums.py
rithm/_crithm.cpython-39-aarch64-linux-gnu.so
rithm/_hints.py
rithm/integer.py
rithm/_rithm.py
rithm/py.typed
rithm-14.6.0.dist-info/top_level.txt
rithm-14.6.0.dist-info/RECORD
rithm-14.6.0.dist-info/LICENSE
rithm-14.6.0.dist-info/METADATA
rithm-14.6.0.dist-info/WHEEL
