Metadata-Version: 2.1
Name: rithm
Version: 14.6.0
Summary: Arbitrary precision arithmetic.
Home-page: https://github.com/lycantropos/rithm/
Download-URL: https://github.com/lycantropos/rithm/archive/master.zip
Author-email: Azat Ibrakov <azatibrakov@gmail.com>
License: MIT License
Classifier: License :: OSI Approved :: MIT License
Classifier: Programming Language :: Python :: 3.9
Classifier: Programming Language :: Python :: 3.10
Classifier: Programming Language :: Python :: 3.11
Classifier: Programming Language :: Python :: 3.12
Classifier: Programming Language :: Python :: 3.13
Classifier: Programming Language :: Python :: Implementation :: CPython
Classifier: Programming Language :: Python :: Implementation :: PyPy
Requires-Python: >=3.9
License-File: LICENSE
Requires-Dist: typing-extensions<5.0,>=4.12.2
Provides-Extra: tests
Requires-Dist: hypothesis<7.0,>=6.118.8; extra == "tests"
Requires-Dist: pytest<9.0,>=8.3.3; extra == "tests"
